crawler_analytics/__init__.py
crawler_analytics/main.py
crawler_analytics/server.py
crawler_analytics-0.1.13.dist-info/METADATA
crawler_analytics-0.1.13.dist-info/WHEEL
crawler_analytics-0.1.13.dist-info/entry_points.txt
crawler_analytics-0.1.13.dist-info/RECORD
